{
  "10058": {
    "basic": {
      "list": [
        {
          "p_no": 10058,
          "leagueType": 10100,
          "t_code": "2002",
          "p_name": "양현종",
          "year": "2024",
          "p_nameEN": "Hyeon-Jong Yang",
          "G": "29",
          "GS": "29",
          "GR": "0",
          "GF": "3",
          "CG": "3",
          "SHO": "0",
          "W": "11",
          "L": "5",
          "S": "0",
          "HD": "0",
          "IP": 171.1,
          "ER": "78",
          "R": "86",
          "TBF": "727",
          "H": "174",
          "2B": "37",
          "3B": "6",
          "HR": "21",
          "BB": "41",
          "HP": "6",
          "IB": "0",
          "SO": "129",
          "ROE": "11",
          "BK": "0",
          "WP": "2",
          "ERA": 4.1,
          "FIP": 4.68571,
          "WHIP": 1.25,
          "WAR": 4.3421319816391675,
          "QS": "15",
          "p_position": 1
        }
      ]
    },
    "deepen": {
      "list": [
        {
          "p_no": 10058,
          "t_code": "2002",
          "p_name": "양현종",
          "year": "2024",
          "K9": 6.776,
          "BB9": 2.154,
          "KBB": "3.1463",
          "HR9": 1.103,
          "OBP": 0.305,
          "SLG": 0.422,
          "OPS": 0.727
        }
      ]
    },
    "result_cd": 100,
    "result_msg": "성공"
  },
  "10126": {
    "basic": {
      "list": [
        {
          "p_no": 10126,
          "leagueType": 10100,
          "t_code": "9002",
          "p_name": "김광현",
          "year": "2024",
          "p_nameEN": "Kwang-Hyun Kim",
          "G": "31",
          "GS": "31",
          "GR": "0",
          "GF": "0",
          "CG": "0",
          "SHO": "0",
          "W": "12",
          "L": "10",
          "S": "0",
          "HD": "0",
          "IP": 162.1,
          "ER": "89",
          "R": "95",
          "TBF": "709",
          "H": "162",
          "2B": "29",
          "3B": "0",
          "HR": "24",
          "BB": "73",
          "HP": "6",
          "IB": "1",
          "SO": "154",
          "ROE": "6",
          "BK": "0",
          "WP": "8",
          "ERA": 4.93,
          "FIP": 5.1766,
          "WHIP": 1.45,
          "WAR": 2.9650592495923753,
          "QS": "13",
          "p_position": 1
        }
      ]
    },
    "deepen": {
      "list": [
        {
          "p_no": 10126,
          "t_code": "9002",
          "p_name": "김광현",
          "year": "2024",
          "K9": 8.538,
          "BB9": 4.047,
          "KBB": "2.1096",
          "HR9": 1.331,
          "OBP": 0.342,
          "SLG": 0.423,
          "OPS": 0.765
        }
      ]
    },
    "result_cd": 100,
    "result_msg": "성공"
  },
  "10131": {
    "basic": {
      "list": [
        {
          "p_no": 10131,
          "leagueType": 10100,
          "t_code": "9002",
          "p_name": "박종훈",
          "year": "2024",
          "p_nameEN": "Jong-Hoon Park",
          "G": "10",
          "GS": "9",
          "GR": "1",
          "GF": "1",
          "CG": "0",
          "SHO": "0",
          "W": "1",
          "L": "4",
          "S": "0",
          "HD": "0",
          "IP": 35,
          "ER": "27",
          "R": "28",
          "TBF": "164",
          "H": "37",
          "2B": "7",
          "3B": "0",
          "HR": "7",
          "BB": "21",
          "HP": "8",
          "IB": "0",
          "SO": "34",
          "ROE": "0",
          "BK": "0",
          "WP": "3",
          "ERA": 6.9399999999999995,
          "FIP": 6.83449,
          "WHIP": 1.6600000000000001,
          "WAR": 0.12373623353647088,
          "QS": "1",
          "p_position": 1
        }
      ]
    },
    "deepen": {
      "list": [
        {
          "p_no": 10131,
          "t_code": "9002",
          "p_name": "박종훈",
          "year": "2024",
          "K9": 8.743,
          "BB9": 5.4,
          "KBB": "1.6190",
          "HR9": 1.8,
          "OBP": 0.402,
          "SLG": 0.485,
          "OPS": 0.887
        }
      ]
    },
    "result_cd": 100,
    "result_msg": "성공"
  },
  "10220": {
    "basic": {
      "list": [
        {
          "p_no": 10220,
          "leagueType": 10100,
          "t_code": "11001",
          "p_name": "이재학",
          "year": "2024",
          "p_nameEN": "Jae-Hak Lee",
          "G": "21",
          "GS": "21",
          "GR": "0",
          "GF": "0",
          "CG": "0",
          "SHO": "0",
          "W": "3",
          "L": "12",
          "S": "0",
          "HD": "0",
          "IP": 104.1,
          "ER": "64",
          "R": "68",
          "TBF": "462",
          "H": "108",
          "2B": "27",
          "3B": "3",
          "HR": "17",
          "BB": "42",
          "HP": "4",
          "IB": "0",
          "SO": "97",
          "ROE": "3",
          "BK": "0",
          "WP": "2",
          "ERA": 5.52,
          "FIP": 5.25719,
          "WHIP": 1.44,
          "WAR": 1.1394350801044402,
          "QS": "7",
          "p_position": 1
        }
      ]
    },
    "deepen": {
      "list": [
        {
          "p_no": 10220,
          "t_code": "11001",
          "p_name": "이재학",
          "year": "2024",
          "K9": 8.367,
          "BB9": 3.623,
          "KBB": "2.3095",
          "HR9": 1.466,
          "OBP": 0.339,
          "SLG": 0.473,
          "OPS": 0.812
        }
      ]
    },
    "result_cd": 100,
    "result_msg": "성공"
  },
  "10363": {
    "basic": {
      "list": [
        {
          "p_no": 10363,
          "leagueType": 10100,
          "t_code": "1001",
          "p_name": "백정현",
          "year": "2024",
          "p_nameEN": "Jung-Hyun Baek",
          "G": "17",
          "GS": "15",
          "GR": "2",
          "GF": "1",
          "CG": "0",
          "SHO": "0",
          "W": "6",
          "L": "5",
          "S": "0",
          "HD": "0",
          "IP": 78.2,
          "ER": "52",
          "R": "56",
          "TBF": "360",
          "H": "104",
          "2B": "15",
          "3B": "2",
          "HR": "13",
          "BB": "27",
          "HP": "1",
          "IB": "1",
          "SO": "56",
          "ROE": "4",
          "BK": "0",
          "WP": "0",
          "ERA": 5.95,
          "FIP": 5.5168,
          "WHIP": 1.67,
          "WAR": 0.8468542896583956,
          "QS": "4",
          "p_position": 1
        }
      ]
    },
    "deepen": {
      "list": [
        {
          "p_no": 10363,
          "t_code": "1001",
          "p_name": "백정현",
          "year": "2024",
          "K9": 6.407,
          "BB9": 3.089,
          "KBB": "2.0741",
          "HR9": 1.487,
          "OBP": 0.37,
          "SLG": 0.497,
          "OPS": 0.867
        }
      ]
    },
    "result_cd": 100,
    "result_msg": "성공"
  },
  "10590": {
    "basic": {
      "list": [
        {
          "p_no": 10590,
          "leagueType": 10100,
          "t_code": "7002",
          "p_name": "류현진",
          "year": "2024",
          "p_nameEN": "Hyun-Jin Ryu",
          "G": "28",
          "GS": "28",
          "GR": "0",
          "GF": "0",
          "CG": "0",
          "SHO": "0",
          "W": "10",
          "L": "8",
          "S": "0",
          "HD": "0",
          "IP": 158.1,
          "ER": "68",
          "R": "78",
          "TBF": "679",
          "H": "182",
          "2B": "22",
          "3B": "1",
          "HR": "12",
          "BB": "33",
          "HP": "3",
          "IB": "0",
          "SO": "135",
          "ROE": "10",
          "BK": "0",
          "WP": "1",
          "ERA": 3.87,
          "FIP": 3.72952,
          "WHIP": 1.3599999999999999,
          "WAR": 3.8390961649180815,
          "QS": "16",
          "p_position": 1
        }
      ]
    },
    "deepen": {
      "list": [
        {
          "p_no": 10590,
          "t_code": "7002",
          "p_name": "류현진",
          "year": "2024",
          "K9": 7.674,
          "BB9": 1.876,
          "KBB": "4.0909",
          "HR9": 0.682,
          "OBP": 0.323,
          "SLG": 0.381,
          "OPS": 0.704
        }
      ]
    },
    "result_cd": 100,
    "result_msg": "성공"
  },
  "10652": {
    "basic": {
      "list": [
        {
          "p_no": 10652,
          "leagueType": 10100,
          "t_code": "5002",
          "p_name": "임찬규",
          "year": "2024",
          "p_nameEN": "Chan-Gyu Im",
          "G": "25",
          "GS": "24",
          "GR": "1",
          "GF": "0",
          "CG": "0",
          "SHO": "0",
          "W": "10",
          "L": "6",
          "S": "0",
          "HD": "1",
          "IP": 134,
          "ER": "57",
          "R": "58",
          "TBF": "577",
          "H": "144",
          "2B": "29",
          "3B": "1",
          "HR": "12",
          "BB": "42",
          "HP": "5",
          "IB": "1",
          "SO": "136",
          "ROE": "0",
          "BK": "0",
          "WP": "1",
          "ERA": 3.83,
          "FIP": 3.85849,
          "WHIP": 1.3900000000000001,
          "WAR": 3.9377569269570203,
          "QS": "11",
          "p_position": 1
        }
      ]
    },
    "deepen": {
      "list": [
        {
          "p_no": 10652,
          "t_code": "5002",
          "p_name": "임찬규",
          "year": "2024",
          "K9": 9.134,
          "BB9": 2.8209999999999997,
          "KBB": "3.2381",
          "HR9": 0.806,
          "OBP": 0.333,
          "SLG": 0.404,
          "OPS": 0.737
        }
      ]
    },
    "result_cd": 100,
    "result_msg": "성공"
  },
  "11222": {
    "basic": {
      "list": [
        {
          "p_no": 11222,
          "leagueType": 10100,
          "t_code": "10001",
          "p_name": "하영민",
          "year": "2024",
          "p_nameEN": "Young-Min Ha",
          "G": "28",
          "GS": "28",
          "GR": "0",
          "GF": "0",
          "CG": "0",
          "SHO": "0",
          "W": "9",
          "L": "8",
          "S": "0",
          "HD": "0",
          "IP": 150.1,
          "ER": "73",
          "R": "82",
          "TBF": "671",
          "H": "168",
          "2B": "33",
          "3B": "6",
          "HR": "8",
          "BB": "58",
          "HP": "5",
          "IB": "0",
          "SO": "101",
          "ROE": "9",
          "BK": "0",
          "WP": "7",
          "ERA": 4.37,
          "FIP": 4.52631,
          "WHIP": 1.5,
          "WAR": 2.7283064141155435,
          "QS": "9",
          "p_position": 1
        }
      ]
    },
    "deepen": {
      "list": [
        {
          "p_no": 11222,
          "t_code": "10001",
          "p_name": "하영민",
          "year": "2024",
          "K9": 6.047,
          "BB9": 3.472,
          "KBB": "1.7414",
          "HR9": 0.479,
          "OBP": 0.345,
          "SLG": 0.396,
          "OPS": 0.741
        }
      ]
    },
    "result_cd": 100,
    "result_msg": "성공"
  },
  "11232": {
    "basic": {
      "list": [
        {
          "p_no": 11232,
          "leagueType": 10100,
          "t_code": "3001",
          "p_name": "이인복",
          "year": "2024",
          "p_nameEN": "In-Bok Lee",
          "G": "8",
          "GS": "6",
          "GR": "2",
          "GF": "1",
          "CG": "0",
          "SHO": "0",
          "W": "0",
          "L": "3",
          "S": "0",
          "HD": "0",
          "IP": 33,
          "ER": "35",
          "R": "35",
          "TBF": "159",
          "H": "49",
          "2B": "14",
          "3B": "0",
          "HR": "10",
          "BB": "13",
          "HP": "3",
          "IB": "0",
          "SO": "20",
          "ROE": "1",
          "BK": "0",
          "WP": "4",
          "ERA": 9.55,
          "FIP": 7.87405,
          "WHIP": 1.88,
          "WAR": -0.3270781194847327,
          "QS": "1",
          "p_position": 1
        }
      ]
    },
    "deepen": {
      "list": [
        {
          "p_no": 11232,
          "t_code": "3001",
          "p_name": "이인복",
          "year": "2024",
          "K9": 5.455,
          "BB9": 3.545,
          "KBB": "1.5385",
          "HR9": 2.727,
          "OBP": 0.411,
          "SLG": 0.679,
          "OPS": 1.09
        }
      ]
    },
    "result_cd": 100,
    "result_msg": "성공"
  },
  "11242": {
    "basic": {
      "list": [
        {
          "p_no": 11242,
          "leagueType": 10100,
          "t_code": "9002",
          "p_name": "이건욱",
          "year": "2024",
          "p_nameEN": "Geon-Wook Lee",
          "G": "10",
          "GS": "2",
          "GR": "8",
          "GF": "1",
          "CG": "0",
          "SHO": "0",
          "W": "1",
          "L": "2",
          "S": "0",
          "HD": "0",
          "IP": 19,
          "ER": "24",
          "R": "25",
          "TBF": "106",
          "H": "34",
          "2B": "4",
          "3B": "0",
          "HR": "5",
          "BB": "15",
          "HP": "2",
          "IB": "0",
          "SO": "17",
          "ROE": "2",
          "BK": "0",
          "WP": "3",
          "ERA": 11.37,
          "FIP": 7.98952,
          "WHIP": 2.58,
          "WAR": -0.5753477393628362,
          "QS": "0",
          "p_position": 1
        }
      ]
    },
    "deepen": {
      "list": [
        {
          "p_no": 11242,
          "t_code": "9002",
          "p_name": "이건욱",
          "year": "2024",
          "K9": 8.053,
          "BB9": 7.105,
          "KBB": "1.1333",
          "HR9": 2.368,
          "OBP": 0.481,
          "SLG": 0.602,
          "OPS": 1.083
        }
      ]
    },
    "result_cd": 100,
    "result_msg": "성공"
  },
  "11308": {
    "basic": {
      "list": [
        {
          "p_no": 11308,
          "leagueType": 10100,
          "t_code": "12001",
          "p_name": "고영표",
          "year": "2024",
          "p_nameEN": "Yeong-Pyo Ko",
          "G": "18",
          "GS": "17",
          "GR": "1",
          "GF": "0",
          "CG": "0",
          "SHO": "0",
          "W": "6",
          "L": "8",
          "S": "0",
          "HD": "0",
          "IP": 100,
          "ER": "55",
          "R": "61",
          "TBF": "456",
          "H": "141",
          "2B": "27",
          "3B": "4",
          "HR": "6",
          "BB": "14",
          "HP": "11",
          "IB": "0",
          "SO": "79",
          "ROE": "4",
          "BK": "1",
          "WP": "2",
          "ERA": 4.95,
          "FIP": 3.77063,
          "WHIP": 1.55,
          "WAR": 1.5566503543218306,
          "QS": "9",
          "p_position": 1
        }
      ]
    },
    "deepen": {
      "list": [
        {
          "p_no": 11308,
          "t_code": "12001",
          "p_name": "고영표",
          "year": "2024",
          "K9": 7.11,
          "BB9": 1.26,
          "KBB": "5.6429",
          "HR9": 0.54,
          "OBP": 0.366,
          "SLG": 0.459,
          "OPS": 0.825
        }
      ]
    },
    "result_cd": 100,
    "result_msg": "성공"
  },
  "11310": {
    "basic": {
      "list": [
        {
          "p_no": 11310,
          "leagueType": 10100,
          "t_code": "3001",
          "p_name": "박세웅",
          "year": "2024",
          "p_nameEN": "Se-Woong Park",
          "G": "30",
          "GS": "30",
          "GR": "0",
          "GF": "0",
          "CG": "0",
          "SHO": "0",
          "W": "6",
          "L": "11",
          "S": "0",
          "HD": "0",
          "IP": 173.1,
          "ER": "92",
          "R": "103",
          "TBF": "759",
          "H": "188",
          "2B": "33",
          "3B": "0",
          "HR": "13",
          "BB": "56",
          "HP": "11",
          "IB": "0",
          "SO": "124",
          "ROE": "12",
          "BK": "0",
          "WP": "10",
          "ERA": 4.78,
          "FIP": 4.57259,
          "WHIP": 1.41,
          "WAR": 3.520348488710914,
          "QS": "14",
          "p_position": 1
        }
      ]
    },
    "deepen": {
      "list": [
        {
          "p_no": 11310,
          "t_code": "3001",
          "p_name": "박세웅",
          "year": "2024",
          "K9": 6.438,
          "BB9": 2.908,
          "KBB": "2.2143",
          "HR9": 0.675,
          "OBP": 0.337,
          "SLG": 0.38,
          "OPS": 0.717
        }
      ]
    },
    "result_cd": 100,
    "result_msg": "성공"
  },
  "11318": {
    "basic": {
      "list": [
        {
          "p_no": 11318,
          "leagueType": 10100,
          "t_code": "12001",
          "p_name": "엄상백",
          "year": "2024",
          "p_nameEN": "Sang-baek Eom ",
          "G": "29",
          "GS": "29",
          "GR": "0",
          "GF": "0",
          "CG": "0",
          "SHO": "0",
          "W": "13",
          "L": "10",
          "S": "0",
          "HD": "0",
          "IP": 156.2,
          "ER": "85",
          "R": "88",
          "TBF": "675",
          "H": "164",
          "2B": "26",
          "3B": "3",
          "HR": "26",
          "BB": "42",
          "HP": "7",
          "IB": "0",
          "SO": "159",
          "ROE": "3",
          "BK": "0",
          "WP": "2",
          "ERA": 4.88,
          "FIP": 4.67014,
          "WHIP": 1.31,
          "WAR": 3.3859604880594936,
          "QS": "9",
          "p_position": 1
        }
      ]
    },
    "deepen": {
      "list": [
        {
          "p_no": 11318,
          "t_code": "12001",
          "p_name": "엄상백",
          "year": "2024",
          "K9": 9.134,
          "BB9": 2.413,
          "KBB": "3.7857",
          "HR9": 1.494,
          "OBP": 0.318,
          "SLG": 0.445,
          "OPS": 0.763
        }
      ]
    },
    "result_cd": 100,
    "result_msg": "성공"
  },
  "11379": {
    "basic": {
      "list": [
        {
          "p_no": 11379,
          "leagueType": 10100,
          "t_code": "5002",
          "p_name": "최원태",
          "year": "2024",
          "p_nameEN": "Won-Tae Choi",
          "G": "24",
          "GS": "23",
          "GR": "1",
          "GF": "0",
          "CG": "0",
          "SHO": "0",
          "W": "9",
          "L": "7",
          "S": "0",
          "HD": "0",
          "IP": 126.2,
          "ER": "60",
          "R": "66",
          "TBF": "554",
          "H": "126",
          "2B": "20",
          "3B": "1",
          "HR": "10",
          "BB": "57",
          "HP": "5",
          "IB": "0",
          "SO": "103",
          "ROE": "6",
          "BK": "0",
          "WP": "5",
          "ERA": 4.26,
          "FIP": 4.70452,
          "WHIP": 1.44,
          "WAR": 2.884872763457828,
          "QS": "10",
          "p_position": 1
        }
      ]
    },
    "deepen": {
      "list": [
        {
          "p_no": 11379,
          "t_code": "5002",
          "p_name": "최원태",
          "year": "2024",
          "K9": 7.318,
          "BB9": 4.05,
          "KBB": "1.8070",
          "HR9": 0.711,
          "OBP": 0.342,
          "SLG": 0.371,
          "OPS": 0.713
        }
      ]
    },
    "result_cd": 100,
    "result_msg": "성공"
  },
  "11410": {
    "basic": {
      "list": [
        {
          "p_no": 11410,
          "leagueType": 10100,
          "t_code": "7002",
          "p_name": "김민우",
          "year": "2024",
          "p_nameEN": "Min-Woo Kim",
          "G": "3",
          "GS": "3",
          "GR": "0",
          "GF": "0",
          "CG": "0",
          "SHO": "0",
          "W": "1",
          "L": "0",
          "S": "0",
          "HD": "0",
          "IP": 12.1,
          "ER": "3",
          "R": "3",
          "TBF": "49",
          "H": "7",
          "2B": "0",
          "3B": "0",
          "HR": "2",
          "BB": "6",
          "HP": "0",
          "IB": "0",
          "SO": "13",
          "ROE": "1",
          "BK": "0",
          "WP": "0",
          "ERA": 2.19,
          "FIP": 5.08298,
          "WHIP": 1.05,
          "WAR": 0.5591378544574579,
          "QS": "1",
          "p_position": 1
        }
      ]
    },
    "deepen": {
      "list": [
        {
          "p_no": 11410,
          "t_code": "7002",
          "p_name": "김민우",
          "year": "2024",
          "K9": 9.486,
          "BB9": 4.378,
          "KBB": "2.1667",
          "HR9": 1.459,
          "OBP": 0.265,
          "SLG": 0.302,
          "OPS": 0.567
        }
      ]
    },
    "result_cd": 100,
    "result_msg": "성공"
  },
  "12295": {
    "basic": {
      "list": [
        {
          "p_no": 12295,
          "leagueType": 10100,
          "t_code": "3001",
          "p_name": "윌커슨",
          "year": "2024",
          "p_nameEN": "Aaron Wilkerson",
          "G": "32",
          "GS": "32",
          "GR": "0",
          "GF": "1",
          "CG": "1",
          "SHO": "1",
          "W": "12",
          "L": "8",
          "S": "0",
          "HD": "0",
          "IP": 196.2,
          "ER": "84",
          "R": "90",
          "TBF": "816",
          "H": "210",
          "2B": "37",
          "3B": "3",
          "HR": "18",
          "BB": "27",
          "HP": "2",
          "IB": "0",
          "SO": "167",
          "ROE": "13",
          "BK": "0",
          "WP": "3",
          "ERA": 3.84,
          "FIP": 3.66976,
          "WHIP": 1.21,
          "WAR": 6.056565445113432,
          "QS": "18",
          "p_position": 1
        }
      ]
    },
    "deepen": {
      "list": [
        {
          "p_no": 12295,
          "t_code": "3001",
          "p_name": "윌커슨",
          "year": "2024",
          "K9": 7.642,
          "BB9": 1.236,
          "KBB": "6.1852",
          "HR9": 0.824,
          "OBP": 0.294,
          "SLG": 0.394,
          "OPS": 0.688
        }
      ]
    },
    "result_cd": 100,
    "result_msg": "성공"
  },
  "12852": {
    "basic": {
      "list": [
        {
          "p_no": 12852,
          "leagueType": 10100,
          "t_code": "6002",
          "p_name": "최원준",
          "year": "2024",
          "p_nameEN": "Won-Jun Choi",
          "G": "24",
          "GS": "24",
          "GR": "0",
          "GF": "0",
          "CG": "0",
          "SHO": "0",
          "W": "6",
          "L": "7",
          "S": "0",
          "HD": "0",
          "IP": 110,
          "ER": "79",
          "R": "79",
          "TBF": "490",
          "H": "125",
          "2B": "24",
          "3B": "2",
          "HR": "21",
          "BB": "34",
          "HP": "10",
          "IB": "1",
          "SO": "72",
          "ROE": "3",
          "BK": "0",
          "WP": "1",
          "ERA": 6.46,
          "FIP": 6.14708,
          "WHIP": 1.45,
          "WAR": 1.1513721277463567,
          "QS": "3",
          "p_position": 1
        }
      ]
    },
    "deepen": {
      "list": [
        {
          "p_no": 12852,
          "t_code": "6002",
          "p_name": "최원준",
          "year": "2024",
          "K9": 5.891,
          "BB9": 2.782,
          "KBB": "2.1176",
          "HR9": 1.718,
          "OBP": 0.346,
          "SLG": 0.489,
          "OPS": 0.835
        }
      ]
    },
    "result_cd": 100,
    "result_msg": "성공"
  },
  "12908": {
    "basic": {
      "list": [
        {
          "p_no": 12908,
          "leagueType": 10100,
          "t_code": "5002",
          "p_name": "손주영",
          "year": "2024",
          "p_nameEN": "Ju-Young Son",
          "G": "28",
          "GS": "27",
          "GR": "1",
          "GF": "0",
          "CG": "0",
          "SHO": "0",
          "W": "9",
          "L": "10",
          "S": "0",
          "HD": "1",
          "IP": 144.2,
          "ER": "61",
          "R": "71",
          "TBF": "637",
          "H": "157",
          "2B": "16",
          "3B": "0",
          "HR": "11",
          "BB": "54",
          "HP": "10",
          "IB": "0",
          "SO": "112",
          "ROE": "9",
          "BK": "0",
          "WP": "6",
          "ERA": 3.79,
          "FIP": 4.61665,
          "WHIP": 1.46,
          "WAR": 3.7794722781942895,
          "QS": "11",
          "p_position": 1
        }
      ]
    },
    "deepen": {
      "list": [
        {
          "p_no": 12908,
          "t_code": "5002",
          "p_name": "손주영",
          "year": "2024",
          "K9": 6.968,
          "BB9": 3.359,
          "KBB": "2.0741",
          "HR9": 0.684,
          "OBP": 0.35,
          "SLG": 0.367,
          "OPS": 0.717
        }
      ]
    },
    "result_cd": 100,
    "result_msg": "성공"
  },
  "12930": {
    "basic": {
      "list": [
        {
          "p_no": 12930,
          "leagueType": 10100,
          "t_code": "3001",
          "p_name": "나균안",
          "year": "2024",
          "p_nameEN": "Gyun-An Na",
          "G": "26",
          "GS": "14",
          "GR": "12",
          "GF": "4",
          "CG": "0",
          "SHO": "0",
          "W": "4",
          "L": "7",
          "S": "0",
          "HD": "0",
          "IP": 73,
          "ER": "69",
          "R": "73",
          "TBF": "380",
          "H": "114",
          "2B": "19",
          "3B": "0",
          "HR": "15",
          "BB": "47",
          "HP": "5",
          "IB": "0",
          "SO": "74",
          "ROE": "2",
          "BK": "0",
          "WP": "10",
          "ERA": 8.51,
          "FIP": 6.42204,
          "WHIP": 2.21,
          "WAR": -0.6786440727386288,
          "QS": "2",
          "p_position": 1
        }
      ]
    },
    "deepen": {
      "list": [
        {
          "p_no": 12930,
          "t_code": "3001",
          "p_name": "나균안",
          "year": "2024",
          "K9": 9.123,
          "BB9": 5.795,
          "KBB": "1.5745",
          "HR9": 1.849,
          "OBP": 0.44,
          "SLG": 0.551,
          "OPS": 0.991
        }
      ]
    },
    "result_cd": 100,
    "result_msg": "성공"
  },
  "13061": {
    "basic": {
      "list": [
        {
          "p_no": 13061,
          "leagueType": 10100,
          "t_code": "6002",
          "p_name": "곽빈",
          "year": "2024",
          "p_nameEN": "Been Gwak",
          "G": "30",
          "GS": "30",
          "GR": "0",
          "GF": "0",
          "CG": "0",
          "SHO": "0",
          "W": "15",
          "L": "9",
          "S": "0",
          "HD": "0",
          "IP": 167.2,
          "ER": "79",
          "R": "83",
          "TBF": "716",
          "H": "142",
          "2B": "29",
          "3B": "1",
          "HR": "11",
          "BB": "76",
          "HP": "6",
          "IB": "0",
          "SO": "154",
          "ROE": "5",
          "BK": "1",
          "WP": "11",
          "ERA": 4.24,
          "FIP": 4.21016,
          "WHIP": 1.3,
          "WAR": 4.387817043056617,
          "QS": "17",
          "p_position": 1
        }
      ]
    },
    "deepen": {
      "list": [
        {
          "p_no": 13061,
          "t_code": "6002",
          "p_name": "곽빈",
          "year": "2024",
          "K9": 8.266,
          "BB9": 4.08,
          "KBB": "2.0263",
          "HR9": 0.59,
          "OBP": 0.315,
          "SLG": 0.332,
          "OPS": 0.647
        }
      ]
    },
    "result_cd": 100,
    "result_msg": "성공"
  },
  "13080": {
    "basic": {
      "list": [
        {
          "p_no": 13080,
          "leagueType": 10100,
          "t_code": "11001",
          "p_name": "김시훈",
          "year": "2024",
          "p_nameEN": "Si-Hoon Kim",
          "G": "39",
          "GS": "18",
          "GR": "21",
          "GF": "0",
          "CG": "0",
          "SHO": "0",
          "W": "3",
          "L": "4",
          "S": "0",
          "HD": "5",
          "IP": 107.1,
          "ER": "54",
          "R": "60",
          "TBF": "477",
          "H": "110",
          "2B": "25",
          "3B": "1",
          "HR": "7",
          "BB": "59",
          "HP": "3",
          "IB": "0",
          "SO": "74",
          "ROE": "7",
          "BK": "1",
          "WP": "1",
          "ERA": 4.53,
          "FIP": 5.13256,
          "WHIP": 1.5699999999999998,
          "WAR": 1.9239900249849025,
          "QS": "3",
          "p_position": 1
        }
      ]
    },
    "deepen": {
      "list": [
        {
          "p_no": 13080,
          "t_code": "11001",
          "p_name": "김시훈",
          "year": "2024",
          "K9": 6.205,
          "BB9": 4.947,
          "KBB": "1.2542",
          "HR9": 0.587,
          "OBP": 0.361,
          "SLG": 0.386,
          "OPS": 0.747
        }
      ]
    },
    "result_cd": 100,
    "result_msg": "성공"
  },
  "13085": {
    "basic": {
      "list": [
        {
          "p_no": 13085,
          "leagueType": 10100,
          "t_code": "11001",
          "p_name": "신민혁",
          "year": "2024",
          "p_nameEN": "Min-Hyuk Shin",
          "G": "25",
          "GS": "24",
          "GR": "1",
          "GF": "1",
          "CG": "0",
          "SHO": "0",
          "W": "8",
          "L": "9",
          "S": "0",
          "HD": "0",
          "IP": 121,
          "ER": "58",
          "R": "67",
          "TBF": "524",
          "H": "140",
          "2B": "24",
          "3B": "3",
          "HR": "20",
          "BB": "16",
          "HP": "7",
          "IB": "0",
          "SO": "74",
          "ROE": "8",
          "BK": "1",
          "WP": "2",
          "ERA": 4.31,
          "FIP": 5.27791,
          "WHIP": 1.29,
          "WAR": 2.6834899364047833,
          "QS": "10",
          "p_position": 1
        }
      ]
    },
    "deepen": {
      "list": [
        {
          "p_no": 13085,
          "t_code": "11001",
          "p_name": "신민혁",
          "year": "2024",
          "K9": 5.504,
          "BB9": 1.19,
          "KBB": "4.6250",
          "HR9": 1.488,
          "OBP": 0.312,
          "SLG": 0.467,
          "OPS": 0.779
        }
      ]
    },
    "result_cd": 100,
    "result_msg": "성공"
  },
  "13092": {
    "basic": {
      "list": [
        {
          "p_no": 13092,
          "leagueType": 10100,
          "t_code": "10001",
          "p_name": "김선기",
          "year": "2024",
          "p_nameEN": "Seon-Gi Kim ",
          "G": "42",
          "GS": "6",
          "GR": "36",
          "GF": "4",
          "CG": "0",
          "SHO": "0",
          "W": "6",
          "L": "4",
          "S": "0",
          "HD": "0",
          "IP": 76.1,
          "ER": "47",
          "R": "51",
          "TBF": "357",
          "H": "91",
          "2B": "18",
          "3B": "0",
          "HR": "13",
          "BB": "30",
          "HP": "6",
          "IB": "1",
          "SO": "43",
          "ROE": "6",
          "BK": "0",
          "WP": "6",
          "ERA": 5.54,
          "FIP": 6.35914,
          "WHIP": 1.5899999999999999,
          "WAR": 0.14511995777061243,
          "QS": "1",
          "p_position": 1
        }
      ]
    },
    "deepen": {
      "list": [
        {
          "p_no": 13092,
          "t_code": "10001",
          "p_name": "김선기",
          "year": "2024",
          "K9": 5.07,
          "BB9": 3.537,
          "KBB": "1.4333",
          "HR9": 1.533,
          "OBP": 0.359,
          "SLG": 0.474,
          "OPS": 0.833
        }
      ]
    },
    "result_cd": 100,
    "result_msg": "성공"
  },
  "13934": {
    "basic": {
      "list": [
        {
          "p_no": 13934,
          "leagueType": 10100,
          "t_code": "5002",
          "p_name": "켈리",
          "year": "2024",
          "p_nameEN": "Casey Patrick Kelly",
          "G": "19",
          "GS": "19",
          "GR": "0",
          "GF": "2",
          "CG": "2",
          "SHO": "1",
          "W": "5",
          "L": "8",
          "S": "0",
          "HD": "0",
          "IP": 113.2,
          "ER": "57",
          "R": "65",
          "TBF": "495",
          "H": "131",
          "2B": "18",
          "3B": "1",
          "HR": "13",
          "BB": "25",
          "HP": "6",
          "IB": "0",
          "SO": "69",
          "ROE": "4",
          "BK": "0",
          "WP": "9",
          "ERA": 4.51,
          "FIP": 4.94776,
          "WHIP": 1.37,
          "WAR": 1.8492238092777014,
          "QS": "11",
          "p_position": 1
        }
      ]
    },
    "deepen": {
      "list": [
        {
          "p_no": 13934,
          "t_code": "5002",
          "p_name": "켈리",
          "year": "2024",
          "K9": 5.463,
          "BB9": 1.979,
          "KBB": "2.7600",
          "HR9": 1.029,
          "OBP": 0.331,
          "SLG": 0.421,
          "OPS": 0.752
        }
      ]
    },
    "result_cd": 100,
    "result_msg": "성공"
  },
  "13941": {
    "basic": {
      "list": [
        {
          "p_no": 13941,
          "leagueType": 10100,
          "t_code": "6002",
          "p_name": "알칸타라",
          "year": "2024",
          "p_nameEN": "Raul Alcántara",
          "G": "12",
          "GS": "12",
          "GR": "0",
          "GF": "0",
          "CG": "0",
          "SHO": "0",
          "W": "2",
          "L": "2",
          "S": "0",
          "HD": "0",
          "IP": 64.1,
          "ER": "34",
          "R": "35",
          "TBF": "270",
          "H": "58",
          "2B": "8",
          "3B": "3",
          "HR": "10",
          "BB": "22",
          "HP": "2",
          "IB": "0",
          "SO": "34",
          "ROE": "3",
          "BK": "0",
          "WP": "0",
          "ERA": 4.76,
          "FIP": 5.95391,
          "WHIP": 1.24,
          "WAR": 1.1542098608684819,
          "QS": "5",
          "p_position": 1
        }
      ]
    },
    "deepen": {
      "list": [
        {
          "p_no": 13941,
          "t_code": "6002",
          "p_name": "알칸타라",
          "year": "2024",
          "K9": 4.756,
          "BB9": 3.078,
          "KBB": "1.5455",
          "HR9": 1.399,
          "OBP": 0.306,
          "SLG": 0.418,
          "OPS": 0.724
        }
      ]
    },
    "result_cd": 100,
    "result_msg": "성공"
  },
  "13942": {
    "basic": {
      "list": [
        {
          "p_no": 13942,
          "leagueType": 10100,
          "t_code": "12001",
          "p_name": "쿠에바스",
          "year": "2024",
          "p_nameEN": "William Enrique Cuevas Osorio",
          "G": "31",
          "GS": "31",
          "GR": "0",
          "GF": "0",
          "CG": "0",
          "SHO": "0",
          "W": "7",
          "L": "12",
          "S": "0",
          "HD": "0",
          "IP": 173.1,
          "ER": "79",
          "R": "86",
          "TBF": "737",
          "H": "158",
          "2B": "36",
          "3B": "3",
          "HR": "17",
          "BB": "59",
          "HP": "7",
          "IB": "4",
          "SO": "154",
          "ROE": "11",
          "BK": "1",
          "WP": "11",
          "ERA": 4.1,
          "FIP": 4.32221,
          "WHIP": 1.25,
          "WAR": 4.409441312716488,
          "QS": "19",
          "p_position": 1
        }
      ]
    },
    "deepen": {
      "list": [
        {
          "p_no": 13942,
          "t_code": "12001",
          "p_name": "쿠에바스",
          "year": "2024",
          "K9": 7.996,
          "BB9": 3.063,
          "KBB": "2.6102",
          "HR9": 0.883,
          "OBP": 0.306,
          "SLG": 0.381,
          "OPS": 0.687
        }
      ]
    },
    "result_cd": 100,
    "result_msg": "성공"
  },
  "14113": {
    "basic": {
      "list": [
        {
          "p_no": 14113,
          "leagueType": 10100,
          "t_code": "1001",
          "p_name": "원태인",
          "year": "2024",
          "p_nameEN": "Tae-In Won",
          "G": "28",
          "GS": "28",
          "GR": "0",
          "GF": "1",
          "CG": "1",
          "SHO": "0",
          "W": "15",
          "L": "6",
          "S": "0",
          "HD": "0",
          "IP": 159.2,
          "ER": "65",
          "R": "68",
          "TBF": "670",
          "H": "150",
          "2B": "29",
          "3B": "3",
          "HR": "17",
          "BB": "42",
          "HP": "7",
          "IB": "1",
          "SO": "119",
          "ROE": "5",
          "BK": "0",
          "WP": "3",
          "ERA": 3.66,
          "FIP": 4.61743,
          "WHIP": 1.2,
          "WAR": 5.219666165694309,
          "QS": "13",
          "p_position": 1
        }
      ]
    },
    "deepen": {
      "list": [
        {
          "p_no": 14113,
          "t_code": "1001",
          "p_name": "원태인",
          "year": "2024",
          "K9": 6.708,
          "BB9": 2.367,
          "KBB": "2.8333",
          "HR9": 0.958,
          "OBP": 0.3,
          "SLG": 0.385,
          "OPS": 0.685
        }
      ]
    },
    "result_cd": 100,
    "result_msg": "성공"
  },
  "14581": {
    "basic": {
      "list": [
        {
          "p_no": 14581,
          "leagueType": 10100,
          "t_code": "9002",
          "p_name": "오원석",
          "year": "2024",
          "p_nameEN": "Won-Seok Oh",
          "G": "29",
          "GS": "25",
          "GR": "4",
          "GF": "1",
          "CG": "0",
          "SHO": "0",
          "W": "6",
          "L": "9",
          "S": "0",
          "HD": "1",
          "IP": 121.2,
          "ER": "68",
          "R": "72",
          "TBF": "550",
          "H": "122",
          "2B": "14",
          "3B": "1",
          "HR": "17",
          "BB": "65",
          "HP": "13",
          "IB": "1",
          "SO": "112",
          "ROE": "6",
          "BK": "0",
          "WP": "3",
          "ERA": 5.03,
          "FIP": 5.6182,
          "WHIP": 1.54,
          "WAR": 2.3113653232901057,
          "QS": "2",
          "p_position": 1
        }
      ]
    },
    "deepen": {
      "list": [
        {
          "p_no": 14581,
          "t_code": "9002",
          "p_name": "오원석",
          "year": "2024",
          "K9": 8.285,
          "BB9": 4.808,
          "KBB": "1.7231",
          "HR9": 1.258,
          "OBP": 0.365,
          "SLG": 0.404,
          "OPS": 0.769
        }
      ]
    },
    "result_cd": 100,
    "result_msg": "성공"
  },
  "14616": {
    "basic": {
      "list": [
        {
          "p_no": 14616,
          "leagueType": 10100,
          "t_code": "1001",
          "p_name": "이승민",
          "year": "2024",
          "p_nameEN": "Seung-Min Lee",
          "G": "25",
          "GS": "8",
          "GR": "17",
          "GF": "6",
          "CG": "0",
          "SHO": "0",
          "W": "1",
          "L": "4",
          "S": "0",
          "HD": "0",
          "IP": 47.1,
          "ER": "45",
          "R": "48",
          "TBF": "237",
          "H": "71",
          "2B": "8",
          "3B": "1",
          "HR": "14",
          "BB": "26",
          "HP": "3",
          "IB": "0",
          "SO": "23",
          "ROE": "5",
          "BK": "0",
          "WP": "1",
          "ERA": 8.56,
          "FIP": 8.49712,
          "WHIP": 2.05,
          "WAR": -0.37685961116980504,
          "QS": "0",
          "p_position": 1
        }
      ]
    },
    "deepen": {
      "list": [
        {
          "p_no": 14616,
          "t_code": "1001",
          "p_name": "이승민",
          "year": "2024",
          "K9": 4.373,
          "BB9": 4.944,
          "KBB": "0.8846",
          "HR9": 2.662,
          "OBP": 0.422,
          "SLG": 0.594,
          "OPS": 1.016
        }
      ]
    },
    "result_cd": 100,
    "result_msg": "성공"
  },
  "14769": {
    "basic": {
      "list": [
        {
          "p_no": 14769,
          "leagueType": 10100,
          "t_code": "6002",
          "p_name": "김동주",
          "year": "2024",
          "p_nameEN": "Dong-Joo Kim",
          "G": "14",
          "GS": "9",
          "GR": "5",
          "GF": "3",
          "CG": "1",
          "SHO": "0",
          "W": "1",
          "L": "3",
          "S": "0",
          "HD": "0",
          "IP": 50,
          "ER": "38",
          "R": "46",
          "TBF": "244",
          "H": "67",
          "2B": "12",
          "3B": "3",
          "HR": "6",
          "BB": "21",
          "HP": "4",
          "IB": "0",
          "SO": "35",
          "ROE": "3",
          "BK": "1",
          "WP": "7",
          "ERA": 6.84,
          "FIP": 5.50963,
          "WHIP": 1.76,
          "WAR": -0.30701273861398504,
          "QS": "0",
          "p_position": 1
        }
      ]
    },
    "deepen": {
      "list": [
        {
          "p_no": 14769,
          "t_code": "6002",
          "p_name": "김동주",
          "year": "2024",
          "K9": 6.3,
          "BB9": 3.7800000000000002,
          "KBB": "1.6667",
          "HR9": 1.08,
          "OBP": 0.379,
          "SLG": 0.484,
          "OPS": 0.863
        }
      ]
    },
    "result_cd": 100,
    "result_msg": "성공"
  },
  "14788": {
    "basic": {
      "list": [
        {
          "p_no": 14788,
          "leagueType": 10100,
          "t_code": "2002",
          "p_name": "이의리",
          "year": "2024",
          "p_nameEN": "Eui-Lee Lee",
          "G": "4",
          "GS": "4",
          "GR": "0",
          "GF": "0",
          "CG": "0",
          "SHO": "0",
          "W": "1",
          "L": "0",
          "S": "0",
          "HD": "0",
          "IP": 13.1,
          "ER": "8",
          "R": "10",
          "TBF": "69",
          "H": "17",
          "2B": "3",
          "3B": "0",
          "HR": "3",
          "BB": "14",
          "HP": "0",
          "IB": "0",
          "SO": "14",
          "ROE": "1",
          "BK": "0",
          "WP": "0",
          "ERA": 5.4,
          "FIP": 7.64413,
          "WHIP": 2.33,
          "WAR": 0.04333643145254296,
          "QS": "0",
          "p_position": 1
        }
      ]
    },
    "deepen": {
      "list": [
        {
          "p_no": 14788,
          "t_code": "2002",
          "p_name": "이의리",
          "year": "2024",
          "K9": 9.45,
          "BB9": 9.45,
          "KBB": "1.0000",
          "HR9": 2.025,
          "OBP": 0.449,
          "SLG": 0.527,
          "OPS": 0.976
        }
      ]
    },
    "result_cd": 100,
    "result_msg": "성공"
  },
  "15011": {
    "basic": {
      "list": [
        {
          "p_no": 15011,
          "leagueType": 10100,
          "t_code": "3001",
          "p_name": "반즈",
          "year": "2024",
          "p_nameEN": "Charlie Barnes",
          "G": "25",
          "GS": "25",
          "GR": "0",
          "GF": "0",
          "CG": "0",
          "SHO": "0",
          "W": "9",
          "L": "6",
          "S": "0",
          "HD": "0",
          "IP": 150.2,
          "ER": "56",
          "R": "59",
          "TBF": "624",
          "H": "140",
          "2B": "17",
          "3B": "4",
          "HR": "18",
          "BB": "46",
          "HP": "5",
          "IB": "0",
          "SO": "171",
          "ROE": "8",
          "BK": "0",
          "WP": "6",
          "ERA": 3.35,
          "FIP": 3.89911,
          "WHIP": 1.23,
          "WAR": 5.766521192136825,
          "QS": "17",
          "p_position": 1
        }
      ]
    },
    "deepen": {
      "list": [
        {
          "p_no": 15011,
          "t_code": "3001",
          "p_name": "반즈",
          "year": "2024",
          "K9": 10.215,
          "BB9": 2.748,
          "KBB": "3.7174",
          "HR9": 1.075,
          "OBP": 0.309,
          "SLG": 0.388,
          "OPS": 0.697
        }
      ]
    },
    "result_cd": 100,
    "result_msg": "성공"
  },
  "15013": {
    "basic": {
      "list": [
        {
          "p_no": 15013,
          "leagueType": 10100,
          "t_code": "7002",
          "p_name": "문동주",
          "year": "2024",
          "p_nameEN": "Dong-Ju Moon",
          "G": "21",
          "GS": "21",
          "GR": "0",
          "GF": "0",
          "CG": "0",
          "SHO": "0",
          "W": "7",
          "L": "7",
          "S": "0",
          "HD": "0",
          "IP": 111.1,
          "ER": "64",
          "R": "71",
          "TBF": "502",
          "H": "148",
          "2B": "25",
          "3B": "3",
          "HR": "14",
          "BB": "38",
          "HP": "4",
          "IB": "1",
          "SO": "96",
          "ROE": "4",
          "BK": "1",
          "WP": "8",
          "ERA": 5.17,
          "FIP": 4.77953,
          "WHIP": 1.67,
          "WAR": 1.4449321157163701,
          "QS": "7",
          "p_position": 1
        }
      ]
    },
    "deepen": {
      "list": [
        {
          "p_no": 15013,
          "t_code": "7002",
          "p_name": "문동주",
          "year": "2024",
          "K9": 7.76,
          "BB9": 3.072,
          "KBB": "2.5263",
          "HR9": 1.1320000000000001,
          "OBP": 0.382,
          "SLG": 0.488,
          "OPS": 0.87
        }
      ]
    },
    "result_cd": 100,
    "result_msg": "성공"
  },
  "15143": {
    "basic": {
      "list": [
        {
          "p_no": 15143,
          "leagueType": 10100,
          "t_code": "12001",
          "p_name": "벤자민",
          "year": "2024",
          "p_nameEN": "Wes Benjamin",
          "G": "28",
          "GS": "28",
          "GR": "0",
          "GF": "0",
          "CG": "0",
          "SHO": "0",
          "W": "11",
          "L": "8",
          "S": "0",
          "HD": "0",
          "IP": 149.2,
          "ER": "77",
          "R": "90",
          "TBF": "639",
          "H": "141",
          "2B": "25",
          "3B": "4",
          "HR": "28",
          "BB": "48",
          "HP": "4",
          "IB": "2",
          "SO": "156",
          "ROE": "12",
          "BK": "0",
          "WP": "4",
          "ERA": 4.63,
          "FIP": 4.94254,
          "WHIP": 1.26,
          "WAR": 2.7077681215177463,
          "QS": "10",
          "p_position": 1
        }
      ]
    },
    "deepen": {
      "list": [
        {
          "p_no": 15143,
          "t_code": "12001",
          "p_name": "벤자민",
          "year": "2024",
          "K9": 9.381,
          "BB9": 2.886,
          "KBB": "3.2500",
          "HR9": 1.6840000000000002,
          "OBP": 0.305,
          "SLG": 0.447,
          "OPS": 0.752
        }
      ]
    },
    "result_cd": 100,
    "result_msg": "성공"
  },
  "15146": {
    "basic": {
      "list": [
        {
          "p_no": 15146,
          "leagueType": 10100,
          "t_code": "7002",
          "p_name": "페냐",
          "year": "2024",
          "p_nameEN": "Félix Ricardo Peña",
          "G": "9",
          "GS": "9",
          "GR": "0",
          "GF": "0",
          "CG": "0",
          "SHO": "0",
          "W": "3",
          "L": "5",
          "S": "0",
          "HD": "0",
          "IP": 37.1,
          "ER": "26",
          "R": "28",
          "TBF": "171",
          "H": "41",
          "2B": "6",
          "3B": "0",
          "HR": "6",
          "BB": "20",
          "HP": "0",
          "IB": "0",
          "SO": "29",
          "ROE": "1",
          "BK": "0",
          "WP": "1",
          "ERA": 6.27,
          "FIP": 5.91645,
          "WHIP": 1.63,
          "WAR": 0.1786515505609682,
          "QS": "2",
          "p_position": 1
        }
      ]
    },
    "deepen": {
      "list": [
        {
          "p_no": 15146,
          "t_code": "7002",
          "p_name": "페냐",
          "year": "2024",
          "K9": 6.991,
          "BB9": 4.821,
          "KBB": "1.4500",
          "HR9": 1.446,
          "OBP": 0.357,
          "SLG": 0.436,
          "OPS": 0.793
        }
      ]
    },
    "result_cd": 100,
    "result_msg": "성공"
  },
  "15153": {
    "basic": {
      "list": [
        {
          "p_no": 15153,
          "leagueType": 10100,
          "t_code": "6002",
          "p_name": "브랜든",
          "year": "2024",
          "p_nameEN": "Brandon David Waddell",
          "G": "14",
          "GS": "14",
          "GR": "0",
          "GF": "0",
          "CG": "0",
          "SHO": "0",
          "W": "7",
          "L": "4",
          "S": "0",
          "HD": "0",
          "IP": 75,
          "ER": "26",
          "R": "34",
          "TBF": "315",
          "H": "75",
          "2B": "11",
          "3B": "2",
          "HR": "3",
          "BB": "11",
          "HP": "4",
          "IB": "0",
          "SO": "75",
          "ROE": "9",
          "BK": "0",
          "WP": "2",
          "ERA": 3.12,
          "FIP": 2.84763,
          "WHIP": 1.15,
          "WAR": 2.1750588505193162,
          "QS": "10",
          "p_position": 1
        }
      ]
    },
    "deepen": {
      "list": [
        {
          "p_no": 15153,
          "t_code": "6002",
          "p_name": "브랜든",
          "year": "2024",
          "K9": 9,
          "BB9": 1.32,
          "KBB": "6.8182",
          "HR9": 0.36,
          "OBP": 0.289,
          "SLG": 0.339,
          "OPS": 0.628
        }
      ]
    },
    "result_cd": 100,
    "result_msg": "성공"
  },
  "15432": {
    "basic": {
      "list": [
        {
          "p_no": 15432,
          "leagueType": 10100,
          "t_code": "2002",
          "p_name": "윤영철",
          "year": "2024",
          "p_nameEN": "Young-Cheol Yoon",
          "G": "18",
          "GS": "18",
          "GR": "0",
          "GF": "0",
          "CG": "0",
          "SHO": "0",
          "W": "7",
          "L": "4",
          "S": "0",
          "HD": "0",
          "IP": 81.2,
          "ER": "38",
          "R": "44",
          "TBF": "362",
          "H": "82",
          "2B": "14",
          "3B": "1",
          "HR": "8",
          "BB": "43",
          "HP": "1",
          "IB": "0",
          "SO": "58",
          "ROE": "7",
          "BK": "0",
          "WP": "1",
          "ERA": 4.19,
          "FIP": 5.34591,
          "WHIP": 1.53,
          "WAR": 1.8894982074754,
          "QS": "3",
          "p_position": 1
        }
      ]
    },
    "deepen": {
      "list": [
        {
          "p_no": 15432,
          "t_code": "2002",
          "p_name": "윤영철",
          "year": "2024",
          "K9": 6.392,
          "BB9": 4.739,
          "KBB": "1.3488",
          "HR9": 0.882,
          "OBP": 0.353,
          "SLG": 0.391,
          "OPS": 0.744
        }
      ]
    },
    "result_cd": 100,
    "result_msg": "성공"
  },
  "15462": {
    "basic": {
      "list": [
        {
          "p_no": 15462,
          "leagueType": 10100,
          "t_code": "9002",
          "p_name": "송영진",
          "year": "2024",
          "p_nameEN": "Young-Jin Song",
          "G": "26",
          "GS": "20",
          "GR": "6",
          "GF": "2",
          "CG": "0",
          "SHO": "0",
          "W": "5",
          "L": "10",
          "S": "0",
          "HD": "0",
          "IP": 99.1,
          "ER": "64",
          "R": "74",
          "TBF": "456",
          "H": "112",
          "2B": "19",
          "3B": "2",
          "HR": "10",
          "BB": "51",
          "HP": "1",
          "IB": "0",
          "SO": "67",
          "ROE": "7",
          "BK": "2",
          "WP": "8",
          "ERA": 5.8,
          "FIP": 5.41854,
          "WHIP": 1.6400000000000001,
          "WAR": 0.822763343800977,
          "QS": "3",
          "p_position": 1
        }
      ]
    },
    "deepen": {
      "list": [
        {
          "p_no": 15462,
          "t_code": "9002",
          "p_name": "송영진",
          "year": "2024",
          "K9": 6.07,
          "BB9": 4.621,
          "KBB": "1.3137",
          "HR9": 0.906,
          "OBP": 0.364,
          "SLG": 0.417,
          "OPS": 0.781
        }
      ]
    },
    "result_cd": 100,
    "result_msg": "성공"
  },
  "15531": {
    "basic": {
      "list": [
        {
          "p_no": 15531,
          "leagueType": 10100,
          "t_code": "10001",
          "p_name": "후라도",
          "year": "2024",
          "p_nameEN": "Ariel Bolívar Jurado Agrazal",
          "G": "30",
          "GS": "30",
          "GR": "0",
          "GF": "0",
          "CG": "0",
          "SHO": "0",
          "W": "10",
          "L": "8",
          "S": "0",
          "HD": "0",
          "IP": 190.1,
          "ER": "71",
          "R": "78",
          "TBF": "779",
          "H": "185",
          "2B": "27",
          "3B": "4",
          "HR": "19",
          "BB": "32",
          "HP": "9",
          "IB": "0",
          "SO": "169",
          "ROE": "12",
          "BK": "1",
          "WP": "3",
          "ERA": 3.36,
          "FIP": 3.88907,
          "WHIP": 1.1400000000000001,
          "WAR": 5.802878277442628,
          "QS": "23",
          "p_position": 1
        }
      ]
    },
    "deepen": {
      "list": [
        {
          "p_no": 15531,
          "t_code": "10001",
          "p_name": "후라도",
          "year": "2024",
          "K9": 7.991,
          "BB9": 1.513,
          "KBB": "5.2813",
          "HR9": 0.898,
          "OBP": 0.293,
          "SLG": 0.381,
          "OPS": 0.674
        }
      ]
    },
    "result_cd": 100,
    "result_msg": "성공"
  },
  "15643": {
    "basic": {
      "list": [
        {
          "p_no": 15643,
          "leagueType": 10100,
          "t_code": "7002",
          "p_name": "산체스",
          "year": "2024",
          "p_nameEN": "Ricardo Jose Sánchez",
          "G": "11",
          "GS": "11",
          "GR": "0",
          "GF": "0",
          "CG": "0",
          "SHO": "0",
          "W": "2",
          "L": "3",
          "S": "0",
          "HD": "0",
          "IP": 53.1,
          "ER": "25",
          "R": "28",
          "TBF": "245",
          "H": "60",
          "2B": "9",
          "3B": "1",
          "HR": "2",
          "BB": "21",
          "HP": "10",
          "IB": "1",
          "SO": "56",
          "ROE": "4",
          "BK": "1",
          "WP": "2",
          "ERA": 4.22,
          "FIP": 3.91288,
          "WHIP": 1.52,
          "WAR": 1.2859074647655164,
          "QS": "2",
          "p_position": 1
        }
      ]
    },
    "deepen": {
      "list": [
        {
          "p_no": 15643,
          "t_code": "7002",
          "p_name": "산체스",
          "year": "2024",
          "K9": 9.45,
          "BB9": 3.544,
          "KBB": "2.6667",
          "HR9": 0.338,
          "OBP": 0.373,
          "SLG": 0.363,
          "OPS": 0.736
        }
      ]
    },
    "result_cd": 100,
    "result_msg": "성공"
  },
  "15644": {
    "basic": {
      "list": [
        {
          "p_no": 15644,
          "leagueType": 10100,
          "t_code": "9002",
          "p_name": "엘리아스",
          "year": "2024",
          "p_nameEN": "Roenis Elías",
          "G": "22",
          "GS": "21",
          "GR": "1",
          "GF": "0",
          "CG": "0",
          "SHO": "0",
          "W": "7",
          "L": "7",
          "S": "0",
          "HD": "0",
          "IP": 123.2,
          "ER": "56",
          "R": "59",
          "TBF": "525",
          "H": "126",
          "2B": "14",
          "3B": "0",
          "HR": "13",
          "BB": "30",
          "HP": "6",
          "IB": "0",
          "SO": "104",
          "ROE": "10",
          "BK": "0",
          "WP": "3",
          "ERA": 4.08,
          "FIP": 4.31168,
          "WHIP": 1.26,
          "WAR": 3.6103183806963988,
          "QS": "10",
          "p_position": 1
        }
      ]
    },
    "deepen": {
      "list": [
        {
          "p_no": 15644,
          "t_code": "9002",
          "p_name": "엘리아스",
          "year": "2024",
          "K9": 7.569,
          "BB9": 2.183,
          "KBB": "3.4667",
          "HR9": 0.946,
          "OBP": 0.315,
          "SLG": 0.376,
          "OPS": 0.691
        }
      ]
    },
    "result_cd": 100,
    "result_msg": "성공"
  },
  "15860": {
    "basic": {
      "list": [
        {
          "p_no": 15860,
          "leagueType": 10100,
          "t_code": "1001",
          "p_name": "코너",
          "year": "2024",
          "p_nameEN": "Connor Seabold",
          "G": "28",
          "GS": "28",
          "GR": "0",
          "GF": "1",
          "CG": "1",
          "SHO": "1",
          "W": "11",
          "L": "6",
          "S": "0",
          "HD": "0",
          "IP": 160,
          "ER": "61",
          "R": "67",
          "TBF": "663",
          "H": "135",
          "2B": "17",
          "3B": "3",
          "HR": "21",
          "BB": "40",
          "HP": "19",
          "IB": "0",
          "SO": "158",
          "ROE": "4",
          "BK": "0",
          "WP": "9",
          "ERA": 3.43,
          "FIP": 4.50475,
          "WHIP": 1.09,
          "WAR": 5.2666814804380895,
          "QS": "13",
          "p_position": 1
        }
      ]
    },
    "deepen": {
      "list": [
        {
          "p_no": 15860,
          "t_code": "1001",
          "p_name": "코너",
          "year": "2024",
          "K9": 8.888,
          "BB9": 2.25,
          "KBB": "3.9500",
          "HR9": 1.181,
          "OBP": 0.293,
          "SLG": 0.37,
          "OPS": 0.663
        }
      ]
    },
    "result_cd": 100,
    "result_msg": "성공"
  },
  "15861": {
    "basic": {
      "list": [
        {
          "p_no": 15861,
          "leagueType": 10100,
          "t_code": "1001",
          "p_name": "레예스",
          "year": "2024",
          "p_nameEN": "Denyi Reyes",
          "G": "26",
          "GS": "26",
          "GR": "0",
          "GF": "0",
          "CG": "0",
          "SHO": "0",
          "W": "11",
          "L": "4",
          "S": "0",
          "HD": "0",
          "IP": 144,
          "ER": "61",
          "R": "65",
          "TBF": "617",
          "H": "159",
          "2B": "21",
          "3B": "3",
          "HR": "15",
          "BB": "30",
          "HP": "7",
          "IB": "0",
          "SO": "114",
          "ROE": "5",
          "BK": "0",
          "WP": "4",
          "ERA": 3.81,
          "FIP": 4.31427,
          "WHIP": 1.31,
          "WAR": 4.465718300718198,
          "QS": "12",
          "p_position": 1
        }
      ]
    },
    "deepen": {
      "list": [
        {
          "p_no": 15861,
          "t_code": "1001",
          "p_name": "레예스",
          "year": "2024",
          "K9": 7.125,
          "BB9": 1.875,
          "KBB": "3.8000",
          "HR9": 0.938,
          "OBP": 0.32,
          "SLG": 0.404,
          "OPS": 0.724
        }
      ]
    },
    "result_cd": 100,
    "result_msg": "성공"
  },
  "16023": {
    "basic": {
      "list": [
        {
          "p_no": 16023,
          "leagueType": 10100,
          "t_code": "5002",
          "p_name": "엔스",
          "year": "2024",
          "p_nameEN": "Dietrich Arthur Enns",
          "G": "30",
          "GS": "30",
          "GR": "0",
          "GF": "0",
          "CG": "0",
          "SHO": "0",
          "W": "13",
          "L": "6",
          "S": "0",
          "HD": "0",
          "IP": 167.2,
          "ER": "78",
          "R": "84",
          "TBF": "714",
          "H": "169",
          "2B": "29",
          "3B": "3",
          "HR": "16",
          "BB": "50",
          "HP": "6",
          "IB": "0",
          "SO": "157",
          "ROE": "9",
          "BK": "0",
          "WP": "4",
          "ERA": 4.19,
          "FIP": 4.09505,
          "WHIP": 1.31,
          "WAR": 3.766282559141343,
          "QS": "13",
          "p_position": 1
        }
      ]
    },
    "deepen": {
      "list": [
        {
          "p_no": 16023,
          "t_code": "5002",
          "p_name": "엔스",
          "year": "2024",
          "K9": 8.427,
          "BB9": 2.684,
          "KBB": "3.1400",
          "HR9": 0.859,
          "OBP": 0.319,
          "SLG": 0.392,
          "OPS": 0.711
        }
      ]
    },
    "result_cd": 100,
    "result_msg": "성공"
  },
  "16027": {
    "basic": {
      "list": [
        {
          "p_no": 16027,
          "leagueType": 10100,
          "t_code": "12001",
          "p_name": "원상현",
          "year": "2024",
          "p_nameEN": "Sang-hyun Won",
          "G": "22",
          "GS": "10",
          "GR": "12",
          "GF": "3",
          "CG": "0",
          "SHO": "0",
          "W": "2",
          "L": "5",
          "S": "0",
          "HD": "1",
          "IP": 65.1,
          "ER": "51",
          "R": "54",
          "TBF": "324",
          "H": "105",
          "2B": "18",
          "3B": "2",
          "HR": "6",
          "BB": "31",
          "HP": "2",
          "IB": "0",
          "SO": "59",
          "ROE": "3",
          "BK": "1",
          "WP": "7",
          "ERA": 7.03,
          "FIP": 4.68316,
          "WHIP": 2.08,
          "WAR": -0.07097402051747295,
          "QS": "1",
          "p_position": 1
        }
      ]
    },
    "deepen": {
      "list": [
        {
          "p_no": 16027,
          "t_code": "12001",
          "p_name": "원상현",
          "year": "2024",
          "K9": 8.128,
          "BB9": 4.27,
          "KBB": "1.9032",
          "HR9": 0.827,
          "OBP": 0.427,
          "SLG": 0.511,
          "OPS": 0.938
        }
      ]
    },
    "result_cd": 100,
    "result_msg": "성공"
  },
  "16064": {
    "basic": {
      "list": [
        {
          "p_no": 16064,
          "leagueType": 10100,
          "t_code": "11001",
          "p_name": "카스타노",
          "year": "2024",
          "p_nameEN": "Daniel Alexander Castano",
          "G": "19",
          "GS": "19",
          "GR": "0",
          "GF": "0",
          "CG": "0",
          "SHO": "0",
          "W": "8",
          "L": "6",
          "S": "0",
          "HD": "0",
          "IP": 111.2,
          "ER": "54",
          "R": "65",
          "TBF": "476",
          "H": "117",
          "2B": "23",
          "3B": "4",
          "HR": "11",
          "BB": "25",
          "HP": "7",
          "IB": "0",
          "SO": "89",
          "ROE": "7",
          "BK": "1",
          "WP": "0",
          "ERA": 4.35,
          "FIP": 4.32835,
          "WHIP": 1.27,
          "WAR": 1.892333275860024,
          "QS": "12",
          "p_position": 1
        }
      ]
    },
    "deepen": {
      "list": [
        {
          "p_no": 16064,
          "t_code": "11001",
          "p_name": "카스타노",
          "year": "2024",
          "K9": 7.173,
          "BB9": 2.015,
          "KBB": "3.5600",
          "HR9": 0.887,
          "OBP": 0.316,
          "SLG": 0.416,
          "OPS": 0.732
        }
      ]
    },
    "result_cd": 100,
    "result_msg": "성공"
  },
  "16065": {
    "basic": {
      "list": [
        {
          "p_no": 16065,
          "leagueType": 10100,
          "t_code": "11001",
          "p_name": "하트",
          "year": "2024",
          "p_nameEN": "Kyle Patrick Hart",
          "G": "26",
          "GS": "26",
          "GR": "0",
          "GF": "0",
          "CG": "0",
          "SHO": "0",
          "W": "13",
          "L": "3",
          "S": "0",
          "HD": "0",
          "IP": 157,
          "ER": "47",
          "R": "51",
          "TBF": "631",
          "H": "124",
          "2B": "16",
          "3B": "1",
          "HR": "11",
          "BB": "38",
          "HP": "11",
          "IB": "0",
          "SO": "182",
          "ROE": "7",
          "BK": "0",
          "WP": "2",
          "ERA": 2.69,
          "FIP": 3.16602,
          "WHIP": 1.03,
          "WAR": 6.150586745388057,
          "QS": "17",
          "p_position": 1
        }
      ]
    },
    "deepen": {
      "list": [
        {
          "p_no": 16065,
          "t_code": "11001",
          "p_name": "하트",
          "year": "2024",
          "K9": 10.433,
          "BB9": 2.178,
          "KBB": "4.7895",
          "HR9": 0.631,
          "OBP": 0.275,
          "SLG": 0.303,
          "OPS": 0.578
        }
      ]
    },
    "result_cd": 100,
    "result_msg": "성공"
  },
  "16087": {
    "basic": {
      "list": [
        {
          "p_no": 16087,
          "leagueType": 10100,
          "t_code": "2002",
          "p_name": "크로우",
          "year": "2024",
          "p_nameEN": "William Chandler Crowe",
          "G": "8",
          "GS": "8",
          "GR": "0",
          "GF": "0",
          "CG": "0",
          "SHO": "0",
          "W": "5",
          "L": "1",
          "S": "0",
          "HD": "0",
          "IP": 40.1,
          "ER": "16",
          "R": "19",
          "TBF": "172",
          "H": "41",
          "2B": "7",
          "3B": "0",
          "HR": "2",
          "BB": "12",
          "HP": "1",
          "IB": "1",
          "SO": "43",
          "ROE": "1",
          "BK": "0",
          "WP": "0",
          "ERA": 3.57,
          "FIP": 3.10849,
          "WHIP": 1.31,
          "WAR": 1.0934892047741822,
          "QS": "1",
          "p_position": 1
        }
      ]
    },
    "deepen": {
      "list": [
        {
          "p_no": 16087,
          "t_code": "2002",
          "p_name": "크로우",
          "year": "2024",
          "K9": 9.595,
          "BB9": 2.678,
          "KBB": "3.5833",
          "HR9": 0.446,
          "OBP": 0.314,
          "SLG": 0.342,
          "OPS": 0.656
        }
      ]
    },
    "result_cd": 100,
    "result_msg": "성공"
  },
  "16088": {
    "basic": {
      "list": [
        {
          "p_no": 16088,
          "leagueType": 10100,
          "t_code": "2002",
          "p_name": "네일",
          "year": "2024",
          "p_nameEN": "James Aubrey Naile",
          "G": "26",
          "GS": "26",
          "GR": "0",
          "GF": "0",
          "CG": "0",
          "SHO": "0",
          "W": "12",
          "L": "5",
          "S": "0",
          "HD": "0",
          "IP": 149.1,
          "ER": "42",
          "R": "69",
          "TBF": "642",
          "H": "154",
          "2B": "27",
          "3B": "1",
          "HR": "11",
          "BB": "35",
          "HP": "9",
          "IB": "0",
          "SO": "138",
          "ROE": "17",
          "BK": "1",
          "WP": "3",
          "ERA": 2.5300000000000002,
          "FIP": 3.74078,
          "WHIP": 1.27,
          "WAR": 4.307810690568332,
          "QS": "13",
          "p_position": 1
        }
      ]
    },
    "deepen": {
      "list": [
        {
          "p_no": 16088,
          "t_code": "2002",
          "p_name": "네일",
          "year": "2024",
          "K9": 8.317,
          "BB9": 2.109,
          "KBB": "3.9429",
          "HR9": 0.663,
          "OBP": 0.31,
          "SLG": 0.364,
          "OPS": 0.674
        }
      ]
    },
    "result_cd": 100,
    "result_msg": "성공"
  },
  "16107": {
    "basic": {
      "list": [
        {
          "p_no": 16107,
          "leagueType": 10100,
          "t_code": "7002",
          "p_name": "황준서",
          "year": "2024",
          "p_nameEN": "Jun-seo Hwang",
          "G": "36",
          "GS": "11",
          "GR": "25",
          "GF": "6",
          "CG": "0",
          "SHO": "0",
          "W": "2",
          "L": "8",
          "S": "0",
          "HD": "1",
          "IP": 72,
          "ER": "43",
          "R": "44",
          "TBF": "341",
          "H": "80",
          "2B": "16",
          "3B": "0",
          "HR": "9",
          "BB": "51",
          "HP": "5",
          "IB": "0",
          "SO": "70",
          "ROE": "1",
          "BK": "1",
          "WP": "3",
          "ERA": 5.38,
          "FIP": 5.77746,
          "WHIP": 1.8199999999999998,
          "WAR": 1.024889148219587,
          "QS": "1",
          "p_position": 1
        }
      ]
    },
    "deepen": {
      "list": [
        {
          "p_no": 16107,
          "t_code": "7002",
          "p_name": "황준서",
          "year": "2024",
          "K9": 8.75,
          "BB9": 6.375,
          "KBB": "1.3725",
          "HR9": 1.125,
          "OBP": 0.401,
          "SLG": 0.441,
          "OPS": 0.842
        }
      ]
    },
    "result_cd": 100,
    "result_msg": "성공"
  },
  "16138": {
    "basic": {
      "list": [
        {
          "p_no": 16138,
          "leagueType": 10100,
          "t_code": "10001",
          "p_name": "헤이수스",
          "year": "2024",
          "p_nameEN": "Enmanuel Jose De Jesus",
          "G": "30",
          "GS": "30",
          "GR": "0",
          "GF": "0",
          "CG": "0",
          "SHO": "0",
          "W": "13",
          "L": "11",
          "S": "0",
          "HD": "0",
          "IP": 171.1,
          "ER": "70",
          "R": "78",
          "TBF": "728",
          "H": "171",
          "2B": "31",
          "3B": "2",
          "HR": "22",
          "BB": "44",
          "HP": "14",
          "IB": "1",
          "SO": "178",
          "ROE": "8",
          "BK": "1",
          "WP": "6",
          "ERA": 3.68,
          "FIP": 4.17618,
          "WHIP": 1.25,
          "WAR": 4.394136893971022,
          "QS": "20",
          "p_position": 1
        }
      ]
    },
    "deepen": {
      "list": [
        {
          "p_no": 16138,
          "t_code": "10001",
          "p_name": "헤이수스",
          "year": "2024",
          "K9": 9.35,
          "BB9": 2.311,
          "KBB": "4.0455",
          "HR9": 1.156,
          "OBP": 0.316,
          "SLG": 0.41,
          "OPS": 0.726
        }
      ]
    },
    "result_cd": 100,
    "result_msg": "성공"
  },
  "16141": {
    "basic": {
      "list": [
        {
          "p_no": 16141,
          "leagueType": 10100,
          "t_code": "9002",
          "p_name": "더거",
          "year": "2024",
          "p_nameEN": "Robert Lee Dugger",
          "G": "6",
          "GS": "6",
          "GR": "0",
          "GF": "0",
          "CG": "0",
          "SHO": "0",
          "W": "0",
          "L": "3",
          "S": "0",
          "HD": "0",
          "IP": 22.2,
          "ER": "32",
          "R": "33",
          "TBF": "116",
          "H": "37",
          "2B": "7",
          "3B": "3",
          "HR": "2",
          "BB": "10",
          "HP": "3",
          "IB": "0",
          "SO": "18",
          "ROE": "1",
          "BK": "0",
          "WP": "0",
          "ERA": 12.71,
          "FIP": 5.13163,
          "WHIP": 2.07,
          "WAR": -0.8389506681770665,
          "QS": "1",
          "p_position": 1
        }
      ]
    },
    "deepen": {
      "list": [
        {
          "p_no": 16141,
          "t_code": "9002",
          "p_name": "더거",
          "year": "2024",
          "K9": 7.147,
          "BB9": 3.971,
          "KBB": "1.8000",
          "HR9": 0.794,
          "OBP": 0.431,
          "SLG": 0.554,
          "OPS": 0.985
        }
      ]
    },
    "result_cd": 100,
    "result_msg": "성공"
  }
}